README.md
setup.py
sheepts/__init__.py
sheepts/data.py
sheepts/testing.py
sheepts/utils.py
sheepts.egg-info/PKG-INFO
sheepts.egg-info/SOURCES.txt
sheepts.egg-info/dependency_links.txt
sheepts.egg-info/requires.txt
sheepts.egg-info/top_level.txt