Metadata-Version: 1.1
Name: sheepts
Version: 0.0.3a0
Summary: Light Time Series Toolbox
Home-page: https://github.com/aliciawyy/sheep
Author: Alice Wang
Author-email: rainingilove@gmail.com
License: MIT
Keywords: pandas time-series toolbox
Platform: UNKNOWN
Classifier: Intended Audience :: Developers
Classifier: Programming Language :: Python :: 2.7
Classifier: Programming Language :: Python :: 3.5
Classifier: Programming Language :: Python :: 3.6
Classifier: License :: OSI Approved :: MIT License
